Metadata-Version: 1.0
Name: FCT
Version: 1.0.4
Summary: Basic Library for Viewing Radio Images
Home-page: http://github.com/Rodot-/FIRST-Cutout-Image-Viewer
Author: John (Jack) T O'Brien
Author-email: john.t.obrien@drexel.edu
License: GNU
Platform: UNKNOWN
